Workbook

Sheet Summary
A1: Cost Category | B1: Monthly Cost (USD) | C1: Percentage | D1: Notes
A2: AgentCore Services | B2: =Calculations!B2 -> #REF! | C2: =B1/$B$8*100 -> #VALUE! | D2: Runtime, Browser, Code Interpreter, Gateway, Observability
A3: Foundation Models (Bedrock) | B3: =Calculations!B3 -> #REF! | C3: =B2/$B$8*100 -> #REF! | D3: Claude 3.5, Haiku, Llama models
A4: Supporting AWS Services | B4: =Calculations!B4 -> #REF! | C4: =B3/$B$8*100 -> #REF! | D4: EC2, Lambda, S3, DynamoDB
A5: Data Transfer & Storage | B5: =Calculations!B5 -> #REF! | C5: =B4/$B$8*100 -> #REF! | D5: Inter-AZ, Internet egress, S3 storage
A6: Monitoring & Logging | B6: =Calculations!B6 -> #REF! | C6: =B5/$B$8*100 -> #REF! | D6: CloudWatch metrics, logs, dashboards
A7: Network Infrastructure | B7: =Calculations!B7 -> #REF! | C7: =B6/$B$8*100 -> #REF! | D7: VPC, NAT Gateway, Load Balancer
A8: Security & Compliance | B8: =Calculations!B8 -> #REF! | C8: =B7/$B$8*100 -> #REF! | D8: KMS, IAM, SSL certificates
A9: TOTAL MONTHLY COST | B9: =SUM(B1:B7) -> #REF! | C9: 100% | D9: Total estimated monthly cost

Sheet Assumptions
A1: Category | B1: Value | C1: Unit | D1: Description
A2: Community Assumptions
A3: Team Size | B3: 10 | C3: People | D3: Number of sandbox users in community
A4: Active Hours per Day | B4: 8 | C4: Hours | D4: Daily active usage hours
A5: Working Days per Month | B5: 22 | C5: Days | D5: Business days per month
A6: Sessions per User per Day | B6: 3 | C6: Sessions | D6: AgentCore sessions per user daily
A7: Average Session Duration | B7: 120 | C7: Seconds | D7: Typical session length
A8: Peak Concurrent Users | B8: 5 | C8: Users | D8: Maximum simultaneous users
A9: Data Storage Growth | B9: 10 | C9: GB/Month | D9: Monthly data accumulation
A10: MODEL USAGE DISTRIBUTION
A11: Claude 3.5 Sonnet | B11: 40 | C11: % | D11: Percentage of model usage
A12: Claude 3.5 Haiku | B12: 30 | C12: % | D12: Percentage of model usage
A13: Llama 3.1 70B | B13: 20 | C13: % | D13: Percentage of model usage
A14: Llama 3.1 8B | B14: 10 | C14: % | D14: Percentage of model usage
A15: Average Input Tokens per Session | B15: 500 | C15: Tokens | D15: Typical prompt size
A16: Average Output Tokens per Session | B16: 300 | C16: Tokens | D16: Typical response size
A17: TECHNICAL SPECIFICATIONS
A18: CPU Usage per Session | B18: 0.5 | C18: vCPU | D18: Processing requirement
A19: Memory Usage per Session | B19: 1 | C19: GB | D19: RAM requirement
A20: Storage per User | B20: 5 | C20: GB | D20: Individual storage allocation
A21: Log Retention Period | B21: 30 | C21: Days | D21: CloudWatch log retention
A22: AWS Region | B22: us-east-1 | C22: Region | D22: Primary deployment region
A23: Availability Zones | B23: 2 | C23: Count | D23: Multi-AZ deployment
A24: VPC CIDR | B24: 10.0.0.0/16 | C24: CIDR | D24: Network address space
A25: Environment Type | B25: Sandbox | C25: Type | D25: Development/learning environment
A26: USAGE PATTERNS
A27: Peak Usage Hours | B27: 9:00-17:00 | C27: Time | D27: Daily peak period
A28: Off-Peak Multiplier | B28: 0.3 | C28: Factor | D28: Usage reduction factor
A29: Weekend Multiplier | B29: 0.1 | C29: Factor | D29: Weekend usage reduction
A30: Growth Rate per Quarter | B30: 15 | C30: % | D30: Quarterly usage growth
A31: Experiment Frequency | B31: 2 | C31: per Week | D31: PoC/PoV experiments per user
A32: Training Session Frequency | B32: 1 | C32: per Month | D32: Formal training sessions

Sheet AWS Pricing
A1: Category | B1: Component | C1: Unit | D1: Current Price (USD) | E1: Region | F1: Last Updated | G1: Notes
A2: AgentCore Runtime | B2: CPU Usage | C2: per vCPU-second | D2: 2.48611e-05 | E2: us-east-1 | F2: 2024-12-01 | G2: Consumption-based billing
A3: AgentCore Runtime | B3: Memory Usage | C3: per GB-second | D3: 2.625e-06 | E3: us-east-1 | F3: 2024-12-01 | G3: Peak memory consumed
A4: AgentCore Browser | B4: CPU Usage | C4: per vCPU-second | D4: 2.48611e-05 | E4: us-east-1 | F4: 2024-12-01 | G4: Same as Runtime pricing
A5: AgentCore Browser | B5: Memory Usage | C5: per GB-second | D5: 2.625e-06 | E5: us-east-1 | F5: 2024-12-01 | G5: Same as Runtime pricing
A6: AgentCore Code Interpreter | B6: CPU Usage | C6: per vCPU-second | D6: 2.48611e-05 | E6: us-east-1 | F6: 2024-12-01 | G6: Same as Runtime pricing
A7: AgentCore Code Interpreter | B7: Memory Usage | C7: per GB-second | D7: 2.625e-06 | E7: us-east-1 | F7: 2024-12-01 | G7: Same as Runtime pricing
A8: AgentCore Gateway | B8: MCP Operations | C8: per operation | D8: 0.001 | E8: us-east-1 | F8: 2024-12-01 | G8: ListTools CallTool operations
A9: AgentCore Gateway | B9: Search Queries | C9: per query | D9: 0.001 | E9: us-east-1 | F9: 2024-12-01 | G9: Semantic search functionality
A10: AgentCore Gateway | B10: Tool Indexing | C10: per tool indexed | D10: 0.001 | E10: us-east-1 | F10: 2024-12-01 | G10: One-time indexing cost
A11: AgentCore Observability | B11: Data Ingestion | C11: per GB | D11: 0.5 | E11: us-east-1 | F11: 2024-12-01 | G11: CloudWatch Logs ingestion
A12: AgentCore Observability | B12: Data Storage | C12: per GB-month | D12: 0.03 | E12: us-east-1 | F12: 2024-12-01 | G12: CloudWatch Logs storage
A13: AgentCore Observability | B13: Queries | C13: per 1000 queries | D13: 0.005 | E13: us-east-1 | F13: 2024-12-01 | G13: Log analysis queries
... A49: Data Transfer Internet 1GB-10TB | B49: Data Transfer | C49: per GB | D49: 0.09 | E49: us-east-1 | F49: 2024-12-01 | G49: Next 9.999TB

Sheet Bill of Materials
A1: Service Category | B1: Component | C1: Quantity | D1: Unit | E1: Monthly Usage | F1: Unit Cost (USD) | G1: Monthly Cost (USD)
A2: AgentCore Services | B2: AgentCore Runtime | C2: =Assumptions!#REF!*Assumptions!B3*Assumptions!B4*Assumptions!B5 -> #REF! | D2: Sessions/Month | E2: =C1 -> Quantity | F2: =([1]AWS_Pricing!E1*Assumptions!B17+[1]AWS_Pricing!E2*Assumptions!#REF!)*Assumptions!B6 -> #REF! | G2: =D1*E1 -> #VALUE!
A3: AgentCore Services | B3: AgentCore Browser | C3: =B1*0.3 -> #VALUE! | D3: Sessions/Month | E3: =C2 -> #REF! | F3: =([1]AWS_Pricing!E3*Assumptions!B17+[1]AWS_Pricing!E4*Assumptions!#REF!)*Assumptions!B6 -> #REF! | G3: =D2*E2 -> #VALUE!
A4: AgentCore Services | B4: AgentCore Code Interpreter | C4: =B1*0.2 -> #VALUE! | D4: Sessions/Month | E4: =C3 -> #VALUE! | F4: =([1]AWS_Pricing!E5*Assumptions!B17+[1]AWS_Pricing!E6*Assumptions!#REF!)*Assumptions!B6 -> #REF! | G4: =D3*E3 -> #VALUE!
A5: AgentCore Services | B5: AgentCore Gateway | C5: =B1*100 -> #VALUE! | D5: Operations/Month | E5: =C4 -> #VALUE! | F5: AWS_Pricing!E7 | G5: =D4*E4 -> #VALUE!
A6: Foundation Models | B6: Claude 3.5 Sonnet | C6: =Assumptions!#REF!/100 -> #REF! | D6: Usage % | E6: =C5 -> #VALUE! | F6: =([1]AWS_Pricing!E13*Assumptions!B14+[1]AWS_Pricing!E14*Assumptions!B15)*C1/1000 -> #REF! | G6: =D5*E5 -> #VALUE!
A7: Foundation Models | B7: Claude 3.5 Haiku | C7: =Assumptions!B11/100 -> 0.4 | D7: Usage % | E7: =C6 -> #REF! | F7: =([1]AWS_Pricing!E15*Assumptions!B14+[1]AWS_Pricing!E16*Assumptions!B15)*C1/1000 -> #REF! | G7: =D6*E6 -> #VALUE!
A8: Foundation Models | B8: Llama 3.1 70B | C8: =Assumptions!B12/100 -> 0.3 | D8: Usage % | E8: =C7 -> 0.4 | F8: =([1]AWS_Pricing!E19*Assumptions!B14+[1]AWS_Pricing!E20*Assumptions!B15)*C1/1000 -> #REF! | G8: =D7*E7 -> #VALUE!
A9: Foundation Models | B9: Llama 3.1 8B | C9: =Assumptions!B13/100 -> 0.2 | D9: Usage % | E9: =C8 -> 0.3 | F9: =([1]AWS_Pricing!E21*Assumptions!B14+[1]AWS_Pricing!E22*Assumptions!B15)*C1/1000 -> #REF! | G9: =D8*E8 -> #VALUE!
A10: Compute Services | B10: EC2 t3.medium | C10: 2 | D10: Instances | E10: =C9*24*Assumptions!B4 -> 38.4 | F10: AWS_Pricing!E25 | G10: =D9*E9 -> #VALUE!
A11: Compute Services | B11: EC2 t4g.small | C11: 1 | D11: Instances | E11: =C10*24*Assumptions!B4 -> 384 | F11: AWS_Pricing!E28 | G11: =D10*E10 -> #VALUE!
A12: Compute Services | B12: Lambda Functions | C12: =B1 -> Component | D12: Invocations/Month | E12: =C11 -> 1 | F12: AWS_Pricing!E30*1 | G12: =D11*E11 -> #VALUE!
A13: Compute Services | B13: Lambda ARM Functions | C13: =B1*0.5 -> #VALUE! | D13: Invocations/Month | E13: =C12 -> Component | F13: AWS_Pricing!E31*1 | G13: =D12*E12 -> #VALUE!
A14: Storage Services | B14: S3 Standard Storage | C14: =Assumptions!B8*Assumptions!#REF! -> #REF! | D14: GB | E14: =C13 -> #VALUE! | F14: AWS_Pricing!E32 | G14: =D13*E13 -> #VALUE!
A15: Storage Services | B15: S3 Standard-IA Storage | C15: =B13*0.3 -> #VALUE! | D15: GB | E15: =C14 -> #REF! | F15: AWS_Pricing!E33 | G15: =D14*E14 -> #VALUE!
A16: Storage Services | B16: S3 API Operations | C16: =B1*1000 -> #VALUE! | D16: API Calls/Month | E16: =C15 -> #VALUE! | F16: AWS_Pricing!E34 | G16: =D15*E15 -> #VALUE!
A17: Database Services | B17: DynamoDB Tables | C17: 3 | D17: Tables | E17: =C16 -> #VALUE! | F17: AWS_Pricing!E38 | G17: =D16*E16 -> #VALUE!
A18: Database Services | B18: DynamoDB Read Units | C18: =B1*10000 -> #VALUE! | D18: RRUs/Month | E18: =C17 -> 3 | F18: AWS_Pricing!E36 | G18: =D17*E17/1000000 -> #VALUE!
A19: Database Services | B19: DynamoDB Write Units | C19: =B1*1000 -> #VALUE! | D19: WRUs/Month | E19: =C18 -> #VALUE! | F19: AWS_Pricing!E37 | G19: =D18*E18/1000000 -> #VALUE!
A20: Monitoring Services | B20: CloudWatch Metrics | C20: =Assumptions!#REF!*5 -> #REF! | D20: Metrics | E20: =C19 -> #VALUE! | F20: AWS_Pricing!E39 | G20: =D19*E19 -> #VALUE!
A21: Monitoring Services | B21: CloudWatch Logs | C21: =B1*0.1 -> #VALUE! | D21: GB/Month | E21: =C20 -> #REF! | F21: AWS_Pricing!E40 | G21: =D20*E20 -> #VALUE!
A22: Monitoring Services | B22: CloudWatch Dashboards | C22: 1 | D22: Dashboards | E22: =C21 -> #VALUE! | F22: AWS_Pricing!E42 | G22: =D21*E21 -> #VALUE!
A23: Network Services | B23: VPC NAT Gateway | C23: 1 | D23: Hours/Month | E23: =C22*24*Assumptions!B4 -> 192 | F23: AWS_Pricing!E43 | G23: =D22*E22 -> #VALUE!
A24: Network Services | B24: Application Load Balancer | C24: 1 | D24: Hours/Month | E24: =C23*24*Assumptions!B4 -> 192 | F24: 100 | G24: =D23*E23 -> #VALUE!
A25: Network Services | B25: Data Transfer | C25: =B1*0.001 -> #VALUE! | D25: GB/Month | E25: =C24 -> 1 | F25: AWS_Pricing!E48 | G25: =D24*E24 -> #VALUE!
A26: Security Services | B26: KMS Keys | C26: 2 | D26: Keys | E26: =C25 -> #VALUE! | F26: 50 | G26: =D25*E25 -> #VALUE!
A27: Security Services | B27: SSL Certificates | C27: 1 | D27: Certificates | E27: =C26 -> 2 | F27: 0 | G27: =D26*E26 -> #VALUE!

Sheet Calculations
A1: Cost Category | B1: Formula/Value | C1: Result (USD) | D1: Notes
A2: AgentCore Services Total | B2: =SUM([2]BOM!F1:F4) -> #REF! | D2: Runtime, Browser, Code Interpreter, Gateway costs
A3: Foundation Models Total | B3: =SUM([2]BOM!F5:F8) -> #REF! | D3: All Bedrock model inference costs
A4: Supporting AWS Services Total | B4: =SUM([2]BOM!F9:F16) -> #REF! | D4: EC2, Lambda, S3, DynamoDB costs
A5: Data Transfer & Storage Total | B5: =SUM([2]BOM!F13:F15,[2]BOM!F24) -> #REF! | D5: Storage and data transfer costs
A6: Monitoring & Logging Total | B6: =SUM([2]BOM!F19:F21) -> #REF! | D6: CloudWatch metrics, logs, dashboards
A7: Network Infrastructure Total | B7: =SUM([2]BOM!F22:F23) -> #REF! | D7: VPC, NAT Gateway, ALB costs
A8: Security & Compliance Total | B8: =SUM([2]BOM!F25:F26) -> #REF! | D8: KMS keys and SSL certificates
A9: TOTAL MONTHLY COST | B9: =B1+B2+B3+B4+B5+B6+B7 -> #VALUE! | D9: Complete monthly cost estimate
A11: BREAKDOWN BY USAGE PATTERN | D11: Cost distribution by usage pattern
A12: Peak Hours Cost (70%) | B12: =B8*0.7 -> #REF! | D12: Business hours (9-5) usage cost
A13: Off-Peak Hours Cost (20%) | B13: =B8*0.2 -> #REF! | D13: After hours usage cost
A14: Weekend Cost (10%) | B14: =B8*0.1 -> #REF! | D14: Weekend usage cost
A16: COST PER USER | D16: Per-user cost metrics
A17: Monthly Cost per User | B17: =B8/Assumptions!#REF! -> #REF! | D17: Total cost divided by team size
A18: Daily Cost per User | B18: =B16/Assumptions!B4 -> 0 | D18: Monthly cost per working day
A19: Cost per Session | B19: =B16/(Assumptions!#REF!*Assumptions!B4*Assumptions!B5) -> #REF! | D19: Cost per individual session
A21: QUARTERLY PROJECTIONS | D21: Growth projections
A22: Q1 Estimate | B22: =B8*3 -> #REF! | D22: Current quarter estimate
A23: Q2 Estimate (15% growth) | B23: =B21*1.15 -> 0 | D23: Next quarter with growth
A24: Q3 Estimate (cumulative) | B24: =B22*1.15 -> #REF! | D24: Third quarter projection
A25: Q4 Estimate (cumulative) | B25: =B23*1.15 -> 0 | D25: Fourth quarter projection

Sheet Scenarios
A1: Scenario | B1: Team Size | C1: Sessions / User / Day | D1: Session Duration (sec) | E1: Model Mix - Claude % | F1: Monthly Cost | G1: Cost / User / Month | H1: Notes
A2: Baseline (Current) | B2: 10 | C2: 3 | D2: 120 | E2: 40 | F2: =Calculations!B8 -> #REF! | G2: =F1/B1 -> #VALUE! | H2: Standard sandbox usage pattern
A3: Light Usage | B3: 5 | C3: 2 | D3: 90 | E3: 30 | F3: =Calculations!B8*0.4 -> #REF! | G3: =F2/B2 -> #REF! | H3: Minimal experimentation
A4: Heavy Usage | B4: 15 | C4: 5 | D4: 180 | E4: 50 | F4: =Calculations!B8*1.8 -> #REF! | G4: =F3/B3 -> #REF! | H4: Active development phase
A5: Training Event | B5: 25 | C5: 8 | D5: 300 | E5: 60 | F5: =Calculations!B8*4.2 -> #REF! | G5: =F4/B4 -> #REF! | H5: Intensive training workshop
A6: Quarter End | B6: 10 | C6: 4 | D6: 150 | E6: 45 | F6: =Calculations!B8*1.3 -> #REF! | G6: =F5/B5 -> #REF! | H6: Month-end reporting spike
A7: Experiment Phase | B7: 20 | C7: 6 | D7: 240 | E7: 40 | F7: =Calculations!B8*2.4 -> #REF! | G7: =F6/B6 -> #REF! | H7: Multiple PoCs running
A8: Production Pilot | B8: 10 | C8: 3 | D8: 120 | E8: 40 | F8: =Calculations!B8*1 -> #REF! | G8: =F7/B7 -> #REF! | H8: Pre-production testing
A9: Full Rollout | B9: 50 | C9: 4 | D9: 180 | E9: 35 | F9: =Calculations!B8*6.5 -> #REF! | G9: =F8/B8 -> #REF! | H9: Full community deployment

Sheet Documentation
A1: Section | B1: Description | C1: Reference/Link | D1: Action Required
A2: OVERVIEW
A6: Purpose | B6: AWS AgentCore cost model for community sandbox environments | C6: README.md | D6: No action
A7: Scope | B7: Learning, experimentation, PoC development | C7: Project charter | D7: No action
A8: Audience | B8: IT architects, finance teams, project managers | C8: Stakeholder list | D8: No action
A9: Last Updated | B9: 2025-10-17 | C9: Version control | D9: Update monthly
A11: KEY ASSUMPTIONS
A14: Environment Type | B14: Sandbox/development, not production | C14: Assumptions worksheet | D14: Validate quarterly
A15: Usage Pattern | B15: Business hours, moderate usage, learning focus | C15: Usage analysis | D15: Monitor continuously
A16: Geographic Region | B16: US East (N. Virginia) - us-east-1 | C16: AWS region selection | D16: No action
A17: Cost Optimization | B17: Basic level, standard configurations | C17: Cost optimization guide | D17: Review quarterly
A19: WORKSHEET DESCRIPTIONS
A22: Summary | B22: Executive dashboard with monthly cost breakdown | C22: Summary worksheet | D22: Update formulas as needed
A23: Assumptions | B23: Project parameters and usage assumptions | C23: Assumptions worksheet | D23: Review monthly
A24: AWS Pricing | B24: Current AWS service pricing (updatable) | C24: AWS Pricing worksheet | D24: Update quarterly
A25: Bill of Materials | B25: Detailed component quantities and specifications | C25: Bill of Materials worksheet | D25: Review monthly
A26: Calculations | B26: Cost formulas and calculations | C26: Calculations worksheet | D26: Validate formulas
A27: Scenarios | B27: Multiple usage scenarios for comparison | C27: Scenarios worksheet | D27: Add new scenarios
A28: Documentation | B28: This reference guide and maintenance notes | C28: Documentation worksheet | D28: Update as needed
A30: COST OPTIMIZATION TIPS
A34: Same-AZ Placement | B34: Deploy services in same AZ to avoid data transfer costs | C34: AWS Well-Architected Framework | D34: Implement as needed
A35: Model Selection | B35: Use appropriate model for task complexity (Haiku vs Sonnet) | C35: Bedrock model comparison | D35: Optimize based on usage
A36: Caching Strategy | B36: Implement response caching to reduce model calls | C36: CloudFront caching | D36: Implement as needed
A37: Resource Right-sizing | B37: Size EC2 instances based on actual usage patterns | C37: CloudWatch metrics | D37: Monitor and adjust
A38: Scheduled Scaling | B38: Scale down during off-hours and weekends | C38: Auto Scaling | D38: Configure as needed
A39: Reserved Instances | B39: Consider RIs for predictable baseline workloads | C39: RI recommendations | D39: Evaluate annually
A40: Spot Instances | B40: Use Spot for non-critical development workloads | C40: EC2 Spot pricing | D40: Consider for dev/test
A42: DATA SOURCES
A46: AWS Pricing Calculator | B46: https://calculator.aws/ | C46: AWS Calculator | D46: Bookmark for reference
A47: Bedrock Pricing | B47: https://aws.amazon.com/bedrock/pricing/ | C47: Bedrock docs | D47: Bookmark for reference
A48: AgentCore Documentation | B48: AWS AgentCore service documentation | C48: AgentCore docs | D48: Bookmark for reference
A49: CloudWatch Pricing | B49: https://aws.amazon.com/cloudwatch/pricing/ | C49: CloudWatch docs | D49: Bookmark for reference
A51: MAINTENANCE
A54: Monthly Review | B54: Review actual vs. estimated costs monthly | C54: Cost analysis report | D54: Schedule monthly
A55: Quarterly Adjustment | B55: Adjust assumptions based on usage patterns | C55: Growth planning | D55: Schedule quarterly
A56: Annual Planning | B56: Plan for growth and new use cases | C56: Budget planning | D56: Schedule annually
A57: Price Updates | B57: Update pricing data quarterly or as needed | C57: Price monitoring | D57: Set alerts
